{
  "source": "guides_hosting-job-listings-and-collecting-applications-a-notion-guide-for-startups",
  "sourceTitle": "Hosting job listings and collecting applications: A Notion guide for startups",
  "sourceUrl": "https://www.notion.com/help/guides/hosting-job-listings-and-collecting-applications-a-notion-guide-for-startups",
  "questions": [
    {
      "id": "guides_hosting-job-listings-and-collecting-applications-a-notion-guide-for-startups-001",
      "question": "What is the primary benefit of using Notion to create a jobs page for a startup?",
      "difficulty": "easy",
      "options": [
        {
          "key": "A",
          "text": "It allows you to store and run backend server code.",
          "correct": false,
          "explanation": "Notion is not a server‑side platform; it is a content‑creation and publishing tool."
        },
        {
          "key": "B",
          "text": "You can build a jobs page quickly without needing engineering support.",
          "correct": true,
          "explanation": "The guide emphasizes that Notion lets non‑technical teams create and publish job listings without a developer."
        },
        {
          "key": "C",
          "text": "It automatically posts jobs to all major job boards.",
          "correct": false,
          "explanation": "Notion does not push listings to external job boards; you must share the published URL yourself."
        },
        {
          "key": "D",
          "text": "It creates a native mobile app for recruiting.",
          "correct": false,
          "explanation": "Notion publishes a web page, not a dedicated mobile application."
        }
      ]
    },
    {
      "id": "guides_hosting-job-listings-and-collecting-applications-a-notion-guide-for-startups-002",
      "question": "When you edit a job listing in your Notion workspace, how does the change appear on the published web page?",
      "difficulty": "easy",
      "options": [
        {
          "key": "A",
          "text": "You must manually republish the page each time.",
          "correct": false,
          "explanation": "The guide states that changes update in real time; no manual republish is needed."
        },
        {
          "key": "B",
          "text": "The change updates automatically and appears instantly on the web page.",
          "correct": true,
          "explanation": "Notion syncs the published version with the workspace in real time."
        },
        {
          "key": "C",
          "text": "Updates are queued and appear after a 24‑hour delay.",
          "correct": false,
          "explanation": "There is no built‑in delay; updates are immediate."
        },
        {
          "key": "D",
          "text": "Only text edits are reflected; media must be re‑uploaded.",
          "correct": false,
          "explanation": "All content types, including images and embeds, update in real time."
        }
      ]
    },
    {
      "id": "guides_hosting-job-listings-and-collecting-applications-a-notion-guide-for-startups-003",
      "question": "Which of the following content types cannot be directly added to a Notion job listing page?",
      "difficulty": "medium",
      "options": [
        {
          "key": "A",
          "text": "Headers",
          "correct": false,
          "explanation": "Headers are a standard block type in Notion and can be added."
        },
        {
          "key": "B",
          "text": "Callouts",
          "correct": false,
          "explanation": "Callouts are a native Notion block, usable in any page."
        },
        {
          "key": "C",
          "text": "Embedded Greenhouse page",
          "correct": false,
          "explanation": "The guide specifically mentions embedding a Greenhouse page via the Create embed option."
        },
        {
          "key": "D",
          "text": "Server‑side scripts",
          "correct": true,
          "explanation": "Notion does not execute custom server‑side code; it only hosts static content blocks."
        }
      ]
    },
    {
      "id": "guides_hosting-job-listings-and-collecting-applications-a-notion-guide-for-startups-004",
      "question": "To maintain brand coherence on a Notion jobs page, which design elements are recommended?",
      "difficulty": "medium",
      "options": [
        {
          "key": "A",
          "text": "Page icons, covers, and colored backgrounds",
          "correct": true,
          "explanation": "The article lists these visual elements as ways to align the page with your brand."
        },
        {
          "key": "B",
          "text": "Only plain text without any visual styling",
          "correct": false,
          "explanation": "Plain text lacks visual branding; the guide encourages richer design."
        },
        {
          "key": "C",
          "text": "Changing the page’s URL to include keywords",
          "correct": false,
          "explanation": "While useful for SEO, URL changes are not a visual branding element discussed in the guide."
        },
        {
          "key": "D",
          "text": "Adding a chatbot widget",
          "correct": false,
          "explanation": "Chatbots are not mentioned as a built‑in Notion feature for job pages."
        }
      ]
    },
    {
      "id": "guides_hosting-job-listings-and-collecting-applications-a-notion-guide-for-startups-005",
      "question": "If you want each job listing to have its own detailed page, what Notion feature should you use?",
      "difficulty": "medium",
      "options": [
        {
          "key": "A",
          "text": "Create a subpage for each listing",
          "correct": true,
          "explanation": "The guide explains that each listing can be turned into a separate page for more details."
        },
        {
          "key": "B",
          "text": "Only use an inline table without subpages",
          "correct": false,
          "explanation": "An inline table holds data but does not automatically give a full page for each entry."
        },
        {
          "key": "C",
          "text": "Link to external websites for each job",
          "correct": false,
          "explanation": "While possible, the guide focuses on keeping details inside Notion subpages."
        },
        {
          "key": "D",
          "text": "Attach a PDF file to each row in a database",
          "correct": false,
          "explanation": "PDF attachments are not the same as a dedicated Notion page with its own layout."
        }
      ]
    },
    {
      "id": "guides_hosting-job-listings-and-collecting-applications-a-notion-guide-for-startups-006",
      "question": "How can you create columns on a Notion jobs page?",
      "difficulty": "medium",
      "options": [
        {
          "key": "A",
          "text": "Write custom HTML code in a code block",
          "correct": false,
          "explanation": "Notion does not allow raw HTML for layout; columns are built with drag‑and‑drop."
        },
        {
          "key": "B",
          "text": "Drag and drop content blocks side‑by‑side",
          "correct": true,
          "explanation": "The guide states that you can create columns by dragging blocks with the mouse."
        },
        {
          "key": "C",
          "text": "Insert a spreadsheet and enable column view",
          "correct": false,
          "explanation": "Spreadsheets display data but do not create visual page columns."
        },
        {
          "key": "D",
          "text": "Install a third‑party plugin that adds column functionality",
          "correct": false,
          "explanation": "Column creation is a native Notion interaction; no plugin is required."
        }
      ]
    },
    {
      "id": "guides_hosting-job-listings-and-collecting-applications-a-notion-guide-for-startups-007",
      "question": "When embedding a Greenhouse job posting using Notion’s \"Create embed\" option, which condition is essential for the embed to work on the published web page?",
      "difficulty": "hard",
      "options": [
        {
          "key": "A",
          "text": "The Greenhouse link must be publicly accessible.",
          "correct": true,
          "explanation": "If the source URL is behind a login or private, the embed cannot render for external visitors."
        },
        {
          "key": "B",
          "text": "The embed must be set to \"private\" in Notion.",
          "correct": false,
          "explanation": "Making an embed private would hide it from the public page, defeating the purpose."
        },
        {
          "key": "C",
          "text": "The Notion page itself must be password protected.",
          "correct": false,
          "explanation": "Password protection would restrict public access to the entire page, including the embed."
        },
        {
          "key": "D",
          "text": "The embed must be uploaded as a PDF file.",
          "correct": false,
          "explanation": "Embeds work with live URLs; a PDF is a static file and not a live embed."
        }
      ]
    },
    {
      "id": "guides_hosting-job-listings-and-collecting-applications-a-notion-guide-for-startups-008",
      "question": "You have already published a Notion jobs page. After updating the cover image in the workspace, what must you do for the new cover to appear on the public version?",
      "difficulty": "hard",
      "options": [
        {
          "key": "A",
          "text": "Republish the page via the Share menu.",
          "correct": false,
          "explanation": "Re‑publishing is unnecessary because Notion syncs changes automatically."
        },
        {
          "key": "B",
          "text": "Do nothing; the change appears automatically.",
          "correct": true,
          "explanation": "The guide specifies that updates are reflected in real time on the web page."
        },
        {
          "key": "C",
          "text": "Delete the public page and create a new one.",
          "correct": false,
          "explanation": "Deleting and recreating is excessive; the system handles updates without this step."
        },
        {
          "key": "D",
          "text": "Ask every visitor to clear their browser cache.",
          "correct": false,
          "explanation": "While caching can affect what a user sees, the page itself updates instantly; users don’t need to clear caches."
        }
      ]
    }
  ]
}